samples/__init__.py
samples/src/__init__.py
samples/src/com/__init__.py
samples/src/com/zoho/__init__.py
samples/src/com/zoho/crm/__init__.py
samples/src/com/zoho/crm/api/__init__.py
samples/src/com/zoho/crm/api/attachments/__init__.py
samples/src/com/zoho/crm/api/attachments/attachment.py
samples/src/com/zoho/crm/api/blue_print/__init__.py
samples/src/com/zoho/crm/api/blue_print/blue_print.py
samples/src/com/zoho/crm/api/bulk_read/__init__.py
samples/src/com/zoho/crm/api/bulk_read/bulk_read.py
samples/src/com/zoho/crm/api/bulk_write/__init__.py
samples/src/com/zoho/crm/api/bulk_write/bulk_write.py
samples/src/com/zoho/crm/api/contact_roles/__init__.py
samples/src/com/zoho/crm/api/contact_roles/contact_role.py
samples/src/com/zoho/crm/api/currencies/__init__.py
samples/src/com/zoho/crm/api/currencies/currency.py
samples/src/com/zoho/crm/api/custom_views/__init__.py
samples/src/com/zoho/crm/api/custom_views/custom_view.py
samples/src/com/zoho/crm/api/fields/__init__.py
samples/src/com/zoho/crm/api/fields/field.py
samples/src/com/zoho/crm/api/file/__init__.py
samples/src/com/zoho/crm/api/file/file.py
samples/src/com/zoho/crm/api/initializer/__init__.py
samples/src/com/zoho/crm/api/initializer/init.py
samples/src/com/zoho/crm/api/initializer/sdk_initializer.py
samples/src/com/zoho/crm/api/layouts/__init__.py
samples/src/com/zoho/crm/api/layouts/layout.py
samples/src/com/zoho/crm/api/modules/__init__.py
samples/src/com/zoho/crm/api/modules/module.py
samples/src/com/zoho/crm/api/notes/__init__.py
samples/src/com/zoho/crm/api/notes/note.py
samples/src/com/zoho/crm/api/notification/__init__.py
samples/src/com/zoho/crm/api/notification/notification.py
samples/src/com/zoho/crm/api/organization/__init__.py
samples/src/com/zoho/crm/api/organization/organization.py
samples/src/com/zoho/crm/api/profiles/__init__.py
samples/src/com/zoho/crm/api/profiles/profile.py
samples/src/com/zoho/crm/api/query/__init__.py
samples/src/com/zoho/crm/api/query/query.py
zcrmsdk-3.2.0.dist-info/METADATA
zcrmsdk-3.2.0.dist-info/WHEEL
zcrmsdk-3.2.0.dist-info/top_level.txt
zcrmsdk-3.2.0.dist-info/RECORD
