Metadata-Version: 2.1
Name: zcrmsdk
Version: 3.2.0
Summary: Zoho CRM SDK for Python developers
Home-page: https://github.com/zoho/zohocrm-python-sdk
Author: Zoho CRM API Team
Author-email: support@zohocrm.com
License: UNKNOWN
Keywords: development,zoho,crm,api,zcrmsdk,sdk,zcrm
Platform: UNKNOWN
Classifier: Development Status :: 5 - Production/Stable
Classifier: Intended Audience :: Developers
Classifier: Topic :: Software Development :: Build Tools
Classifier: Programming Language :: Python :: 3
Classifier: Programming Language :: Python :: 3.3
Classifier: Programming Language :: Python :: 3.4
Classifier: Programming Language :: Python :: 3.5
Classifier: Programming Language :: Python :: 3.6
Classifier: Programming Language :: Python :: 3.7
Classifier: Programming Language :: Python :: 3.8
Requires-Dist: requests
Requires-Dist: python-dateutil
Requires-Dist: urllib3
